{"assets":{"C6F507A8D4E2DAF33749643A25A3665A":{"type":"texture","index":47,"assetRequest":{"type":"slide","state":"outgoing","slide":"D836087C-15FC-4FD4-85B5-D75578C69AFC"},"url":"assets/C6F507A8D4E2DAF33749643A25A3665A.png","width":1280,"height":720},"7FD96FD65160E41977E3C562FFAC604F":{"type":"texture","index":48,"assetRequest":{"type":"slide","state":"incoming","slide":"none"},"url":"assets/7FD96FD65160E41977E3C562FFAC604F.svg","width":1280,"height":720}},"events":[{"effects":[{"beginTime":0,"baseLayer":{"animations":[],"initialState":{"affineTransform":[1,0,0,1,0,0],"masksToBounds":true,"rotation":0,"scale":1,"position":{"pointX":640,"pointY":360},"width":1280,"sublayerTransform":[1,0,0,0,0,1,0,0,0,0,1,0,0,0,0,1],"contentsRect":{"y":0,"x":0,"width":1,"height":1},"opacity":1,"edgeAntialiasingMask":0,"height":720,"hidden":false,"anchorPoint":{"pointX":0.5,"pointY":0.5}},"objectID":"0","layers":[{"animations":[],"initialState":{"affineTransform":[1,0,0,1,0,0],"masksToBounds":false,"rotation":0,"scale":1,"position":{"pointX":640,"pointY":360},"width":1280,"sublayerTransform":[1,0,0,0,0,1,0,0,0,0,1,-0.0005251186870016398,0,0,0,1],"contentsRect":{"y":0,"x":0,"width":1,"height":1},"opacity":1,"edgeAntialiasingMask":15,"height":720,"hidden":false,"anchorPoint":{"pointX":0.5,"pointY":0.5}},"layers":[{"animations":[],"layers":[],"initialState":{"affineTransform":[1,0,0,1,0,0],"masksToBounds":false,"rotation":0,"scale":1,"position":{"pointX":640,"pointY":360},"width":1280,"sublayerTransform":[1,0,0,0,0,1,0,0,0,0,1,0,0,0,0,1],"contentsRect":{"y":0,"x":0,"width":1,"height":1},"opacity":1,"edgeAntialiasingMask":0,"height":720,"hidden":false,"anchorPoint":{"pointX":0.5,"pointY":0.5}},"texture":"7FD96FD65160E41977E3C562FFAC604F"},{"animations":[{"from":{"scalar":false},"beginTime":0,"repeatCount":0,"fillMode":"both","property":"hidden","duration":0.01,"to":{"scalar":true}}],"layers":[],"initialState":{"affineTransform":[1,0,0,1,0,0],"masksToBounds":false,"rotation":0,"scale":1,"position":{"pointX":640,"pointY":360},"width":1280,"sublayerTransform":[1,0,0,0,0,1,0,0,0,0,1,0,0,0,0,1],"contentsRect":{"y":0,"x":0,"width":1,"height":1},"opacity":1,"edgeAntialiasingMask":0,"height":720,"hidden":false,"anchorPoint":{"pointX":0.5,"pointY":0.5}},"texture":"C6F507A8D4E2DAF33749643A25A3665A"}]}]},"effects":[],"duration":0.01,"type":"transition","name":"none","objectID":"0"}],"automaticPlay":false,"hyperlinks":[],"accessibility":[{"text":"Don’t rip off your peers ","targetRectangle":{"y":88,"x":84,"width":729.5759999999997,"height":152.8406941932917}},{"text":"Get inspiration","targetRectangle":{"y":242.9291951698542,"x":84,"width":446.6879999999999,"height":152.8406941932917}},{"text":"Make it your own","targetRectangle":{"y":397.8583903397084,"x":84,"width":531.2879999999999,"height":152.8406941932917}},{"text":"Give credit to your sources","targetRectangle":{"y":552.7875855095626,"x":84,"width":829.6559999999998,"height":152.8406941932917}}],"baseLayer":{"animations":[],"initialState":{"affineTransform":[1,0,0,1,0,0],"masksToBounds":true,"rotation":0,"scale":1,"position":{"pointX":640,"pointY":360},"width":1280,"sublayerTransform":[1,0,0,0,0,1,0,0,0,0,1,0,0,0,0,1],"contentsRect":{"y":0,"x":0,"width":1,"height":1},"opacity":1,"edgeAntialiasingMask":0,"height":720,"hidden":false,"anchorPoint":{"pointX":0.5,"pointY":0.5}},"objectID":"0","layers":[{"animations":[],"initialState":{"affineTransform":[1,0,0,1,0,0],"masksToBounds":false,"rotation":0,"scale":1,"position":{"pointX":640,"pointY":360},"width":1280,"sublayerTransform":[1,0,0,0,0,1,0,0,0,0,1,-0.0005251186870016398,0,0,0,1],"contentsRect":{"y":0,"x":0,"width":1,"height":1},"opacity":1,"edgeAntialiasingMask":15,"height":720,"hidden":false,"anchorPoint":{"pointX":0.5,"pointY":0.5}},"layers":[{"animations":[],"layers":[],"initialState":{"affineTransform":[1,0,0,1,0,0],"masksToBounds":false,"rotation":0,"scale":1,"position":{"pointX":640,"pointY":360},"width":1280,"sublayerTransform":[1,0,0,0,0,1,0,0,0,0,1,0,0,0,0,1],"contentsRect":{"y":0,"x":0,"width":1,"height":1},"opacity":1,"edgeAntialiasingMask":0,"height":720,"hidden":false,"anchorPoint":{"pointX":0.5,"pointY":0.5}},"texture":"C6F507A8D4E2DAF33749643A25A3665A"}]}]}}]}